oval/VERSION
oval/__init__.py
oval/__main__.py
oval/oval.py
im_openapi_validator-1.0.1.dist-info/LICENSE
im_openapi_validator-1.0.1.dist-info/METADATA
im_openapi_validator-1.0.1.dist-info/WHEEL
im_openapi_validator-1.0.1.dist-info/entry_points.txt
im_openapi_validator-1.0.1.dist-info/top_level.txt
im_openapi_validator-1.0.1.dist-info/RECORD
