Metadata-Version: 2.1
Name: im-openapi-validator
Version: 1.0.1
Summary: The IM OpenAPI Validator
Home-page: https://github.com/informaticsmatters/openapi-validator
Author: Alan Christie
Author-email: achristie@informaticsmatters.com
License: MIT
Keywords: configuration
Platform: any
Classifier: Development Status :: 5 - Production/Stable
Classifier: Environment :: Console
Classifier: Intended Audience :: Developers
Classifier: License :: OSI Approved :: MIT License
Classifier: Programming Language :: Python :: 3.10
Classifier: Topic :: System :: Installation/Setup
Classifier: Operating System :: POSIX :: Linux
License-File: LICENSE
Requires-Dist: openapi-core (==0.14.4)
